CHANGELOG.rst
CONTRIBUTING.rst
LICENSE
README.md
facelift/__init__.py
facelift/_data.py
facelift/capture.py
facelift/constants.py
facelift/detect.py
facelift/encode.py
facelift/helpers.py
facelift/magic.py
facelift/render.py
facelift/transform.py
facelift/types.py
facelift/window.py
pyproject.toml
facelift-0.2.1.dist-info/LICENSE
facelift-0.2.1.dist-info/WHEEL
facelift-0.2.1.dist-info/METADATA
facelift-0.2.1.dist-info/RECORD
