Metadata-Version: 2.1
Name: facelift
Version: 0.2.1
Summary: A simple wrapper for face detection and recognition
Home-page: https://github.com/stephen-bunn/facelift
License: ISC
Keywords: facelift,face,feature,detection,recognition,dlib,opencv
Author: Stephen Bunn
Author-email: stephen@bunn.io
Requires-Python: >=3.7,<4.0
Classifier: Development Status :: 3 - Alpha
Classifier: Intended Audience :: Developers
Classifier: License :: OSI Approved
Classifier: License :: OSI Approved :: ISC License (ISCL)
Classifier: Natural Language :: English
Classifier: Operating System :: MacOS :: MacOS X
Classifier: Operating System :: Microsoft :: Windows
Classifier: Operating System :: POSIX
Classifier: Programming Language :: Python :: 3
Classifier: Programming Language :: Python :: 3.7
Classifier: Programming Language :: Python :: 3.8
Classifier: Topic :: Software Development :: Libraries :: Python Modules
Provides-Extra: profile
Requires-Dist: attrs (>=20.2.0,<21.0.0)
Requires-Dist: cached-property (>=1.5.2,<2.0.0)
Requires-Dist: dlib (>=19.21.0,<20.0.0)
Requires-Dist: numpy (>=1.19.2,<2.0.0)
Requires-Dist: opencv-python (>=4.4.0,<5.0.0)
Requires-Dist: python-magic (>=0.4.18,<0.5.0); sys_platform != "win32"
Requires-Dist: python-magic-bin (>=0.4.14,<0.5.0); sys_platform == "win32"
Requires-Dist: typing-extensions (>=3.7.4,<4.0.0)
Requires-Dist: urllib3 (>=1.25.11,<2.0.0)
Project-URL: Bug Tracker, https://github.com/stephen-bunn/facelift/issues
Project-URL: Documentation, https://facelift.readthedocs.io
Project-URL: Repository, https://github.com/stephen-bunn/facelift
